odoo/addons/partner_delivery_schedule/README.rst
odoo/addons/partner_delivery_schedule/__init__.py
odoo/addons/partner_delivery_schedule/__manifest__.py
odoo/addons/partner_delivery_schedule/i18n/es.po
odoo/addons/partner_delivery_schedule/i18n/it.po
odoo/addons/partner_delivery_schedule/i18n/nl.po
odoo/addons/partner_delivery_schedule/i18n/partner_delivery_schedule.pot
odoo/addons/partner_delivery_schedule/i18n/zh_CN.po
odoo/addons/partner_delivery_schedule/models/__init__.py
odoo/addons/partner_delivery_schedule/models/partner_delivery_schedule.py
odoo/addons/partner_delivery_schedule/models/res_partner.py
odoo/addons/partner_delivery_schedule/readme/CONTRIBUTORS.md
odoo/addons/partner_delivery_schedule/readme/DESCRIPTION.md
odoo/addons/partner_delivery_schedule/readme/USAGE.md
odoo/addons/partner_delivery_schedule/security/ir.model.access.csv
odoo/addons/partner_delivery_schedule/static/description/icon.png
odoo/addons/partner_delivery_schedule/static/description/index.html
odoo/addons/partner_delivery_schedule/tests/__init__.py
odoo/addons/partner_delivery_schedule/tests/test_partner_delivery_schedule.py
odoo/addons/partner_delivery_schedule/views/partner_delivery_schedule_view.xml
odoo/addons/partner_delivery_schedule/views/report_shipping.xml
odoo/addons/partner_delivery_schedule/views/res_partner_view.xml
odoo_addon_partner_delivery_schedule-18.0.1.0.1.2.dist-info/METADATA
odoo_addon_partner_delivery_schedule-18.0.1.0.1.2.dist-info/WHEEL
odoo_addon_partner_delivery_schedule-18.0.1.0.1.2.dist-info/top_level.txt
odoo_addon_partner_delivery_schedule-18.0.1.0.1.2.dist-info/RECORD
